[
  {
    "DisplayName": "Server IP",
    "Category": "Headless Client",
    "FieldName": "HC_SERVER_IP",
    "InputType": "text",
    "DefaultValue": "127.0.0.1"
  },
  {
    "DisplayName": "Server Port",
    "Category": "Headless Client",
    "FieldName": "HC_SERVER_PORT",
    "InputType": "number",
    "DefaultValue": "2302"
  },
  {
    "DisplayName": "Client Mods (-mod)",
    "Category": "Headless Client",
    "FieldName": "CLIENT_MODS",
    "InputType": "text",
    "DefaultValue": ""
  },
  {
    "DisplayName": "Creator DLCs (-cdlc)",
    "Category": "Headless Client",
    "FieldName": "CDLC",
    "InputType": "text",
    "DefaultValue": ""
  },
  {
    "DisplayName": "Extra HC Parameters",
    "Category": "Headless Client",
    "FieldName": "HC_EXTRA_ARGS",
    "InputType": "text",
    "DefaultValue": ""
  }
]
